{
  "$schema": "http://json-schema.org/draft-07/schema#",
  "definitions": {
    "ssf": {
      "type": "object",
      "properties": {
        "type": { "const": "ssf" },
        "eventRetention": { "type": "string" },
        "jwtFederationProviders":{ "type": "string" },

        "providerSsfId": { "type": "string" },
        "signingKey": { "type": "string" }
      }
    },
    "scim": {
      "type": "object",
      "properties": {
        "type": { "const": "scim" },
        "compatibilityMode": { "type": "string" },
        "dryRun": { "type": "boolean" },
        "excludeUsersServiceAccount": { "type": "boolean" },
        "filterGroup": { "type": "string" },

        "propertyMappings":{ "type": "string" },
        "propertyMappingsGroups":{ "type": "string" },
        "providerScimId": { "type": "string" },
        "token": { "type": "string" },
        "url": { "type": "string" }
      },
      "required": ["token", "url"]
    },
    "saml": {
      "type": "object",
      "properties": {
        "type": { "const": "saml" },
        "acsUrl": { "type": "string" },
        "assertionValidNotBefore": { "type": "string" },
        "assertionValidNotOnOrAfter": { "type": "string" },
        "audience": { "type": "string" },
        "authenticationFlow": { "type": "string" },
        "authnContextClassRefMapping": { "type": "string" },
        "authorizationFlow": { "type": "string" },
        "defaultRelayState": { "type": "string" },
        "digestAlgorithm": { "type": "string" },
        "encryptionKp": { "type": "string" },
        "invalidationFlow": { "type": "string" },
        "issuer": { "type": "string" },

        "nameIdMapping": { "type": "string" },
        "propertyMappings":{ "type": "string" },
        "providerSamlId": { "type": "string" },
        "sessionValidNotOnOrAfter": { "type": "string" },
        "signAssertion": { "type": "boolean" },
        "signResponse": { "type": "boolean" },
        "signatureAlgorithm": { "type": "string" },
        "signingKp": { "type": "string" },
        "spBinding": { "type": "string" },
        "urlSloPost": { "type": "string" },
        "urlSloRedirect": { "type": "string" },
        "urlSsoInit": { "type": "string" },
        "urlSsoPost": { "type": "string" },
        "urlSsoRedirect": { "type": "string" },
        "verificationKp": { "type": "string" }
      },
      "required": ["acsUrl"]
    },
    "proxy": {
      "type": "object",
      "properties": {
        "type": { "const": "proxy" },
        "accessTokenValidity": { "type": "string" },
        "authenticationFlow": { "type": "string" },
        "authorizationFlow": { "type": "string" },

        "basicAuthEnabled": { "type": "boolean" },
        "basicAuthPasswordAttribute": { "type": "string" },
        "basicAuthUsernameAttribute": { "type": "string" },
        "cookieDomain": { "type": "string" },
        "externalHost": { "type": "string" },
        "interceptHeaderAuth": { "type": "boolean" },
        "internalHost": { "type": "string" },
        "internalHostSslValidation": { "type": "boolean" },
        "invalidationFlow": { "type": "string" },
        "jwksSources":{ "type": "string" },
        "jwtFederationProviders":{ "type": "string" },
        "jwtFederationSources":{ "type": "string" },
        "mode": {
          "type": "string",
          "enum": ["proxy", "forward_single", "forward_domain"]
        },
        "name": { "type": "string" },
        "propertyMappings":{ "type": "string" },
        "providerProxyId": { "type": "string" },
        "refreshTokenValidity": { "type": "string" },
        "logoutUri": { "type": "string" },
        "skipPathRegex": { "type": "string" }
      }
    },
    "radius": {
      "type": "object",
      "properties": {
        "type": { "const": "radius" },
        "authorizationFlow": { "type": "string" },
        "clientNetworks": { "type": "string" },
        "invalidationFlow": { "type": "string" },
        "mfaSupport": { "type": "boolean" },

        "propertyMappings":{ "type": "string" },
        "providerRadiusId": { "type": "string" },
        "sharedSecret": { "type": "string" }
      },
      "required": ["sharedSecret"]
    },
    "rac": {
      "type": "object",
      "properties": {
        "type": { "const": "rac" },
        "authenticationFlow": { "type": "string" },
        "authorizationFlow": { "type": "string" },
        "connectionExpiry": { "type": "string" },

        "propertyMappings":{ "type": "string" },
        "providerRacId": { "type": "string" },
        "settings": { "type": "string" }
      }
    },
    "oauth2": {
      "type": "object",
      "properties": {
        "type": { "const": "oauth2" },
        "accessCodeValidity": { "type": "string" },
        "accessTokenValidity": { "type": "string" },
        "allowedRedirectUris":{ "type": "string" },
        "authenticationFlow": { "type": "string" },
        "authorizationFlow": { "type": "string" },
        "clientId": { "type": "string" },
        "clientSecret": { "type": "string" },
        "clientType": { "type": "string" },
        "encryptionKey": { "type": "string" },
        "includeClaimsInIdToken": { "type": "boolean" },
        "invalidationFlow": { "type": "string" },
        "issuerMode": { "type": "string" },
        "jwksSources": { "type": "string" },
        "jwtFederationProviders":{ "type": "string" },
        "jwtFederationSources":{ "type": "string" },

        "propertyMappings":{ "type": "string" },
        "providerOauth2Id": { "type": "string" },
        "refreshTokenValidity": { "type": "string" },
        "logoutUri": { "type": "string" },
        "signingKey": { "type": "string" },
        "subMode": { "type": "string" }
      },
      "required": []
    },
    "microsoftEntra": {
      "type": "object",
      "properties": {
        "type": { "const": "microsoftEntra" },
        "clientId": { "type": "string" },
        "clientSecret": { "type": "string" },
        "dryRun": { "type": "boolean" },
        "excludeUsersServiceAccount": { "type": "boolean" },
        "filterGroup": { "type": "string" },
        "groupDeleteAction": { "type": "string" },

        "propertyMappings":{ "type": "string" },
        "propertyMappingsGroups":{ "type": "string" },
        "providerMicrosoftEntraId": { "type": "string" },
        "tenantId": { "type": "string" },
        "userDeleteAction": { "type": "string" }
      },
      "required": ["clientId", "clientSecret", "tenantId"]
    },
    "ldap": {
      "type": "object",
      "properties": {
        "type": { "const": "ldap" },
        "baseDn": { "type": "string" },
        "bindFlow": { "type": "string" },
        "bindMode": { "type": "string" },
        "certificate": { "type": "string" },
        "gidStartstring": { "type": "string" },
        "mfaSupport": { "type": "boolean" },

        "providerLdapId": { "type": "string" },
        "searchMode": { "type": "string" },
        "tlsServerName": { "type": "string" },
        "uidStartstring": { "type": "string" },
        "unbindFlow": { "type": "string" }
      },
      "required": ["baseDn"]
    },
    "googleWorkspace": {
      "type": "object",
      "properties": {
        "type": { "const": "googleWorkspace" },
        "credentials": { "type": "string" },
        "defaultGroupEmailDomain": { "type": "string" },
        "delegatedSubject": { "type": "string" },
        "dryRun": { "type": "boolean" },
        "excludeUsersServiceAccount": { "type": "boolean" },
        "filterGroup": { "type": "string" },
        "groupDeleteAction": { "type": "string" },

        "propertyMappings":{ "type": "string" },
        "propertyMappingsGroups":{ "type": "string" },
        "providerGoogleWorkspaceId": { "type": "string" },
        "userDeleteAction": { "type": "string" }
      },
      "required": ["defaultGroupEmailDomain"]
    }
  }
}
